gdrove/__init__.py
gdrove/__main__.py
gdrove/common.py
gdrove/drivetodrive.py
gdrove/drivetolocal.py
gdrove/helpers.py
gdrove/localtodrive.py
gdrove/run.py
GDrove-1.2.1.dist-info/LICENSE
GDrove-1.2.1.dist-info/METADATA
GDrove-1.2.1.dist-info/WHEEL
GDrove-1.2.1.dist-info/entry_points.txt
GDrove-1.2.1.dist-info/top_level.txt
GDrove-1.2.1.dist-info/RECORD
